profitpulse/__init__.py
profitpulse/cli/__init__.py
profitpulse/cli/adapters.py
profitpulse/cli/main.py
profitpulse/data/__init__.py
profitpulse/data/assets.py
profitpulse/data/assets_test.py
profitpulse/data/assets_view.py
profitpulse/data/assets_views_test.py
profitpulse/data/categories.py
profitpulse/data/data.py
profitpulse/data/expenses_view.py
profitpulse/data/expenses_view_test.py
profitpulse/data/pulse_view.py
profitpulse/data/pulse_view_test.py
profitpulse/data/sellers.py
profitpulse/data/sellers_test.py
profitpulse/gateways/__init__.py
profitpulse/gateways/cgdfile.py
profitpulse/gateways/cgdfile_test.py
profitpulse/gui/__init__.py
profitpulse/gui/main.py
profitpulse/infrastructure/__init__.py
profitpulse/infrastructure/migrations.py
profitpulse/lib/__init__.py
profitpulse/lib/asset.py
profitpulse/lib/asset_name.py
profitpulse/lib/money.py
profitpulse/lib/seller.py
profitpulse/lib/transaction.py
profitpulse/lib/year_month_day.py
profitpulse/migrations/0.0.0.sql
profitpulse/migrations/2.5.0.sql
profitpulse/migrations/__init__.py
profitpulse/services/__init__.py
profitpulse/services/acquire_asset.py
profitpulse/services/acquire_asset_test.py
profitpulse/services/assign_category.py
profitpulse/services/assign_category_test.py
profitpulse/services/delete_asset.py
profitpulse/services/delete_asset_test.py
profitpulse/services/deposit_into_asset.py
profitpulse/services/deposit_into_asset_test.py
profitpulse/services/divest_asset.py
profitpulse/services/divest_asset_test.py
profitpulse/services/errors.py
profitpulse/services/import_transactions.py
profitpulse/services/revalue_asset.py
profitpulse/services/revalue_test.py
profitpulse/services/services.py
profitpulse/testrig/__init__.py
profitpulse/testrig/factory.py
profitpulse/testrig/fixtures.py
profitpulse/testrig/scenario.py
profitpulse/turbofan.py
profitpulse-2.5.0.dist-info/LICENSE
profitpulse-2.5.0.dist-info/METADATA
profitpulse-2.5.0.dist-info/WHEEL
profitpulse-2.5.0.dist-info/entry_points.txt
profitpulse-2.5.0.dist-info/RECORD
